{
    "Version": "2012-10-17",
    "Statement": [
        {
            "Sid": "LambdaManage",
            "Effect": "Allow",
            "Action": [
                "lambda:CreateFunction",
                "lambda:UpdateFunctionCode",
                "lambda:UpdateFunctionConfiguration",
                "lambda:GetFunction",
                "lambda:GetFunctionConfiguration",
                "lambda:TagResource",
                "lambda:UntagResource"
            ],
            "Resource": "*"
        },
        {
            "Sid": "PassLambdaExecutionRole",
            "Effect": "Allow",
            "Action": "iam:PassRole",
            "Resource": "arn:aws:iam::650961196544:role/role-do-mark-lambdastep-sagemaker"
        }
    ]
}